quick_fuoss
