Metadata-Version: 2.1
Name: quick-fuoss
Version: 0.1.4
Summary: rapid estimation of ion-pair dissociation constants
Home-page: https://github.com/corinwagen/quick-fuoss
Author: Corin Wagen
Author-email: corin.wagen@gmail.com
License: Apache 2.0
Platform: UNKNOWN
Classifier: Programming Language :: Python :: 3
Classifier: Development Status :: 3 - Alpha
Classifier: License :: OSI Approved :: Apache Software License
Classifier: Intended Audience :: Science/Research
Requires-Python: >=3.6
License-File: LICENSE
